{
  "Maharashtra": [
    { "name": "Ahmednagar", "description": "Known for forts and sugar industry." },
    { "name": "Akola", "description": "Cotton city of Maharashtra." },
    { "name": "Amravati", "description": "Cultural and educational hub of Vidarbha region." },
    { "name": "Aurangabad", "description": "Home to Ajanta and Ellora Caves." },
    { "name": "Beed", "description": "Historic district with ancient temples." },
    { "name": "Bhandara", "description": "Known as 'District of Lakes' in Vidarbha." },
    { "name": "Buldhana", "description": "Location of Lonar Crater Lake." },
    { "name": "Chandrapur", "description": "Known for Tadoba Tiger Reserve." },
    { "name": "Dhule", "description": "Located in Khandesh region, rich in agriculture." },
    { "name": "Gadchiroli", "description": "Forested region known for biodiversity." },
    { "name": "Gondia", "description": "Known as 'Rice City' of Maharashtra." },
    { "name": "Hingoli", "description": "Historic city with Narsi Namdev temple." },
    { "name": "Jalgaon", "description": "Banana city of India." },
    { "name": "Jalna", "description": "Known for steel and agriculture industries." },
    { "name": "Kolhapur", "description": "Famous for Mahalakshmi Temple and chappals." },
    { "name": "Latur", "description": "Educational hub of Marathwada." },
    { "name": "Mumbai City", "description": "Financial capital and entertainment hub of India." },
    { "name": "Mumbai Suburban", "description": "Major part of Mumbai metropolitan area." },
    { "name": "Nagpur", "description": "Orange City and geographical center of India." },
    { "name": "Nanded", "description": "Famous for Takht Sri Hazur Sahib Gurudwara." },
    { "name": "Nandurbar", "description": "Tribal district with Satpura ranges." },
    { "name": "Nashik", "description": "Wine capital of India, rich in mythology." },
    { "name": "Osmanabad", "description": "Known for Tuljapur Bhavani Temple." },
    { "name": "Palghar", "description": "Coastal district near Mumbai." },
    { "name": "Parbhani", "description": "Agricultural center of Marathwada." },
    { "name": "Pune", "description": "Cultural and educational capital of Maharashtra." },
    { "name": "Raigad", "description": "Historic fort of Shivaji Maharaj located here." },
    { "name": "Ratnagiri", "description": "Famous for Alphonso mangoes and Konkan beaches." },
    { "name": "Sangli", "description": "Sugar and turmeric production hub." },
    { "name": "Satara", "description": "Famous for Kaas Plateau and forts." },
    { "name": "Sindhudurg", "description": "Coastal district with scenic beaches and forts." },
    { "name": "Solapur", "description": "Famous for textile industries and Siddheshwar Temple." },
    { "name": "Thane", "description": "Part of Mumbai metropolitan region, highly urbanized." },
    { "name": "Wardha", "description": "Associated with Mahatma Gandhi’s ashram at Sevagram." },
    { "name": "Washim", "description": "Ancient place known as Vatsagulma." },
    { "name": "Yavatmal", "description": "Known for cotton and tiger reserves nearby." }
  ]
}
